ezpk/__init__.py
ezpk/ezpk.py
ezpk_ezez-0.0.3.dist-info/LICENSE
ezpk_ezez-0.0.3.dist-info/METADATA
ezpk_ezez-0.0.3.dist-info/WHEEL
ezpk_ezez-0.0.3.dist-info/top_level.txt
ezpk_ezez-0.0.3.dist-info/RECORD
